github_cat
