Metadata-Version: 2.1
Name: github_cat
Version: 0.0.3
Summary: github tools
Home-page: https://www.linkedin.com/in/chandlersong/
Author: chandler song
Author-email: 275737875@qq.com
License: MIT
Keywords: github api tool by token
Platform: all
Classifier: Intended Audience :: Developers
Classifier: Operating System :: OS Independent
Classifier: Natural Language :: Chinese (Simplified)
Classifier: Programming Language :: Python :: 3.7
Classifier: Programming Language :: Python :: 3.8
Classifier: Programming Language :: Python :: 3.9
Classifier: Programming Language :: Python :: 3.10
Classifier: Topic :: Software Development :: Libraries
License-File: LICENSE
Requires-Dist: requests
Requires-Dist: pandas
Requires-Dist: colorama
Requires-Dist: GitPython
Requires-Dist: pandas
Requires-Dist: openpyxl
